{"stage1":[{"objectName":"kyousitu","translate":{"x":0.0,"y":0.0,"z":0.0},"rotate":{"x":-0.0,"y":0.0,"z":0.0},"scale":{"x":1.0,"y":1.0,"z":1.0}},{"objectName":"bg_steel_footing","translate":{"x":928.0,"y":-339.0,"z":-153.0},"rotate":{"x":-0.0,"y":0.0,"z":0.0},"scale":{"x":1.0,"y":1.0,"z":1.0}},{"objectName":"bg_steel_footing","translate":{"x":1955.0,"y":-339.0,"z":-153.0},"rotate":{"x":-0.0,"y":0.0,"z":0.0},"scale":{"x":1.0,"y":1.0,"z":1.0}},{"objectName":"huusya_hasira","translate":{"x":1029.0,"y":-924.0,"z":-64.0},"rotate":{"x":0.0,"y":0.0,"z":180.0},"scale":{"x":0.0599,"y":0.0599,"z":0.0599}},{"objectName":"bg_floating_island_small","translate":{"x":1069.0,"y":-914.0,"z":-95.0},"rotate":{"x":-0.0,"y":0.0,"z":0.0},"scale":{"x":1.0,"y":1.0,"z":1.0}},{"objectName":"huusya_hane","translate":{"x":1030.0,"y":-891.0,"z":339.0},"rotate":{"x":-0.0,"y":0.0,"z":0.0},"scale":{"x":0.1000,"y":0.1000,"z":0.1000}}]}